neighbormodels/__init__.py
neighbormodels/interactions.py
neighbormodels/neighbors.py
neighbormodels/structure.py
neighbormodels-0.2.0.dist-info/LICENSE
neighbormodels-0.2.0.dist-info/METADATA
neighbormodels-0.2.0.dist-info/WHEEL
neighbormodels-0.2.0.dist-info/top_level.txt
neighbormodels-0.2.0.dist-info/RECORD
