Metadata-Version: 2.1
Name: neighbormodels
Version: 0.2.0
Summary: A tool for building crystal lattice models with distance-dependent neighbor interactions.
Home-page: https://github.com/jkglasbrenner/datamaterials-neighbormodels
Author: James K. Glasbrenner
Author-email: jglasbr2@gmu.edu
License: MIT
Project-URL: Documentation, https://neighbormodels.readthedocs.io
Project-URL: Code, https://github.com/jkglasbrenner/datamaterials-neighbormodels
Platform: UNKNOWN
Requires-Python: >=3.6
Requires-Dist: numpy
Requires-Dist: pandas
Requires-Dist: pymatgen
Provides-Extra: docs
Requires-Dist: sphinx ; extra == 'docs'
Requires-Dist: sphinx-rtd-theme ; extra == 'docs'
